tradescope/__init__.py
tradescope/__main__.py
tradescope/constants.py
tradescope/exceptions.py
tradescope/main.py
tradescope/misc.py
tradescope/tradescopebot.py
tradescope/wallets.py
tradescope/worker.py
tradescope/commands/__init__.py
tradescope/commands/analyze_commands.py
tradescope/commands/arguments.py
tradescope/commands/build_config_commands.py
tradescope/commands/cli_options.py
tradescope/commands/data_commands.py
tradescope/commands/db_commands.py
tradescope/commands/deploy_commands.py
tradescope/commands/hyperopt_commands.py
tradescope/commands/list_commands.py
tradescope/commands/optimize_commands.py
tradescope/commands/pairlist_commands.py
tradescope/commands/plot_commands.py
tradescope/commands/strategy_utils_commands.py
tradescope/commands/trade_commands.py
tradescope/commands/webserver_commands.py
tradescope/configuration/__init__.py
tradescope/configuration/config_secrets.py
tradescope/configuration/config_setup.py
tradescope/configuration/config_validation.py
tradescope/configuration/configuration.py
tradescope/configuration/deprecated_settings.py
tradescope/configuration/detect_environment.py
tradescope/configuration/directory_operations.py
tradescope/configuration/environment_vars.py
tradescope/configuration/load_config.py
tradescope/configuration/timerange.py
tradescope/data/__init__.py
tradescope/data/btanalysis.py
tradescope/data/dataprovider.py
tradescope/data/entryexitanalysis.py
tradescope/data/metrics.py
tradescope/data/converter/__init__.py
tradescope/data/converter/converter.py
tradescope/data/converter/trade_converter.py
tradescope/data/converter/trade_converter_kraken.py
tradescope/data/history/__init__.py
tradescope/data/history/history_utils.py
tradescope/data/history/datahandlers/__init__.py
tradescope/data/history/datahandlers/featherdatahandler.py
tradescope/data/history/datahandlers/hdf5datahandler.py
tradescope/data/history/datahandlers/idatahandler.py
tradescope/data/history/datahandlers/jsondatahandler.py
tradescope-2024.4.dist-info/LICENSE
tradescope-2024.4.dist-info/METADATA
tradescope-2024.4.dist-info/WHEEL
tradescope-2024.4.dist-info/entry_points.txt
tradescope-2024.4.dist-info/top_level.txt
tradescope-2024.4.dist-info/RECORD
