Metadata-Version: 2.1
Name: tradescope
Version: 2024.4
Summary: Tradescope - Crypto Trading Bot
Home-page: https://github.com/khulnasoft/tradescope
Author: KhulnaSoft Team
Author-email: KhulnaSoft Team <info@khulnasoft.com>
License: GPLv3
Project-URL: Homepage, https://github.com/khulnasoft/tradescope
Project-URL: Documentation, https://tradescope.khulnasoft.com
Project-URL: Bug Tracker, https://github.com/khulnasoft/tradescope/issues
Classifier: Environment :: Console
Classifier: Intended Audience :: Science/Research
Classifier: License :: OSI Approved :: GNU General Public License v3 (GPLv3)
Classifier: Programming Language :: Python :: 3.9
Classifier: Programming Language :: Python :: 3.10
Classifier: Programming Language :: Python :: 3.11
Classifier: Programming Language :: Python :: 3.12
Classifier: Operating System :: MacOS
Classifier: Operating System :: Unix
Classifier: Topic :: Office/Business :: Financial :: Investment
Requires-Python: >=3.9
License-File: LICENSE
Requires-Dist: ccxt >=4.2.47
Requires-Dist: SQLAlchemy >=2.0.6
Requires-Dist: python-telegram-bot >=20.1
Requires-Dist: arrow >=1.0.0
Requires-Dist: cachetools
Requires-Dist: requests
Requires-Dist: httpx >=0.24.1
Requires-Dist: urllib3
Requires-Dist: jsonschema
Requires-Dist: numpy
Requires-Dist: pandas
Requires-Dist: TA-Lib
Requires-Dist: pandas-ta
Requires-Dist: technical
Requires-Dist: tabulate
Requires-Dist: pycoingecko
Requires-Dist: py-find-1st
Requires-Dist: python-rapidjson
Requires-Dist: orjson
Requires-Dist: colorama
Requires-Dist: jinja2
Requires-Dist: questionary
Requires-Dist: prompt-toolkit
Requires-Dist: joblib >=1.2.0
Requires-Dist: rich
Requires-Dist: fastapi
Requires-Dist: pydantic >=2.2.0
Requires-Dist: pyjwt
Requires-Dist: websockets
Requires-Dist: uvicorn
Requires-Dist: psutil
Requires-Dist: schedule
Requires-Dist: janus
Requires-Dist: ast-comments
Requires-Dist: aiofiles
Requires-Dist: aiohttp
Requires-Dist: cryptography
Requires-Dist: sdnotify
Requires-Dist: python-dateutil
Requires-Dist: pytz
Requires-Dist: packaging
Requires-Dist: tradescope-client
Requires-Dist: pyarrow ; platform_machine != "armv7l"
Provides-Extra: all
Requires-Dist: plotly >=4.0 ; extra == 'all'
Requires-Dist: coveralls ; extra == 'all'
Requires-Dist: isort ; extra == 'all'
Requires-Dist: mypy ; extra == 'all'
Requires-Dist: pre-commit ; extra == 'all'
Requires-Dist: pytest-asyncio ; extra == 'all'
Requires-Dist: pytest-cov ; extra == 'all'
Requires-Dist: pytest-mock ; extra == 'all'
Requires-Dist: pytest-random-order ; extra == 'all'
Requires-Dist: pytest ; extra == 'all'
Requires-Dist: ruff ; extra == 'all'
Requires-Dist: time-machine ; extra == 'all'
Requires-Dist: types-cachetools ; extra == 'all'
Requires-Dist: types-filelock ; extra == 'all'
Requires-Dist: types-python-dateutiltypes-requests ; extra == 'all'
Requires-Dist: types-tabulate ; extra == 'all'
Requires-Dist: jupyter ; extra == 'all'
Requires-Dist: nbstripout ; extra == 'all'
Requires-Dist: ipykernel ; extra == 'all'
Requires-Dist: nbconvert ; extra == 'all'
Requires-Dist: scipy ; extra == 'all'
Requires-Dist: scikit-learn ; extra == 'all'
Requires-Dist: ft-scikit-optimize >=0.9.2 ; extra == 'all'
Requires-Dist: filelock ; extra == 'all'
Requires-Dist: tables ; extra == 'all'
Requires-Dist: blosc ; extra == 'all'
Requires-Dist: joblib ; extra == 'all'
Requires-Dist: lightgbm ; extra == 'all'
Requires-Dist: xgboost ; extra == 'all'
Requires-Dist: tensorboard ; extra == 'all'
Requires-Dist: datasieve >=0.1.5 ; extra == 'all'
Requires-Dist: torch ; extra == 'all'
Requires-Dist: gymnasium ; extra == 'all'
Requires-Dist: stable-baselines3 ; extra == 'all'
Requires-Dist: sb3-contrib ; extra == 'all'
Requires-Dist: tqdm ; extra == 'all'
Requires-Dist: catboost ; (platform_machine != "aarch64") and extra == 'all'
Provides-Extra: dev
Requires-Dist: plotly >=4.0 ; extra == 'dev'
Requires-Dist: coveralls ; extra == 'dev'
Requires-Dist: isort ; extra == 'dev'
Requires-Dist: mypy ; extra == 'dev'
Requires-Dist: pre-commit ; extra == 'dev'
Requires-Dist: pytest-asyncio ; extra == 'dev'
Requires-Dist: pytest-cov ; extra == 'dev'
Requires-Dist: pytest-mock ; extra == 'dev'
Requires-Dist: pytest-random-order ; extra == 'dev'
Requires-Dist: pytest ; extra == 'dev'
Requires-Dist: ruff ; extra == 'dev'
Requires-Dist: time-machine ; extra == 'dev'
Requires-Dist: types-cachetools ; extra == 'dev'
Requires-Dist: types-filelock ; extra == 'dev'
Requires-Dist: types-python-dateutiltypes-requests ; extra == 'dev'
Requires-Dist: types-tabulate ; extra == 'dev'
Requires-Dist: jupyter ; extra == 'dev'
Requires-Dist: nbstripout ; extra == 'dev'
Requires-Dist: ipykernel ; extra == 'dev'
Requires-Dist: nbconvert ; extra == 'dev'
Requires-Dist: scipy ; extra == 'dev'
Requires-Dist: scikit-learn ; extra == 'dev'
Requires-Dist: ft-scikit-optimize >=0.9.2 ; extra == 'dev'
Requires-Dist: filelock ; extra == 'dev'
Requires-Dist: tables ; extra == 'dev'
Requires-Dist: blosc ; extra == 'dev'
Requires-Dist: joblib ; extra == 'dev'
Requires-Dist: lightgbm ; extra == 'dev'
Requires-Dist: xgboost ; extra == 'dev'
Requires-Dist: tensorboard ; extra == 'dev'
Requires-Dist: datasieve >=0.1.5 ; extra == 'dev'
Requires-Dist: torch ; extra == 'dev'
Requires-Dist: gymnasium ; extra == 'dev'
Requires-Dist: stable-baselines3 ; extra == 'dev'
Requires-Dist: sb3-contrib ; extra == 'dev'
Requires-Dist: tqdm ; extra == 'dev'
Requires-Dist: catboost ; (platform_machine != "aarch64") and extra == 'dev'
Provides-Extra: hdf5
Requires-Dist: tables ; extra == 'hdf5'
Requires-Dist: blosc ; extra == 'hdf5'
Provides-Extra: hyperopt
Requires-Dist: scipy ; extra == 'hyperopt'
Requires-Dist: scikit-learn ; extra == 'hyperopt'
Requires-Dist: ft-scikit-optimize >=0.9.2 ; extra == 'hyperopt'
Requires-Dist: filelock ; extra == 'hyperopt'
Provides-Extra: jupyter
Requires-Dist: jupyter ; extra == 'jupyter'
Requires-Dist: nbstripout ; extra == 'jupyter'
Requires-Dist: ipykernel ; extra == 'jupyter'
Requires-Dist: nbconvert ; extra == 'jupyter'
Provides-Extra: plot
Requires-Dist: plotly >=4.0 ; extra == 'plot'
Provides-Extra: tradeai
Requires-Dist: scikit-learn ; extra == 'tradeai'
Requires-Dist: joblib ; extra == 'tradeai'
Requires-Dist: lightgbm ; extra == 'tradeai'
Requires-Dist: xgboost ; extra == 'tradeai'
Requires-Dist: tensorboard ; extra == 'tradeai'
Requires-Dist: datasieve >=0.1.5 ; extra == 'tradeai'
Requires-Dist: catboost ; (platform_machine != "aarch64") and extra == 'tradeai'
Provides-Extra: tradeai_rl
Requires-Dist: torch ; extra == 'tradeai_rl'
Requires-Dist: gymnasium ; extra == 'tradeai_rl'
Requires-Dist: stable-baselines3 ; extra == 'tradeai_rl'
Requires-Dist: sb3-contrib ; extra == 'tradeai_rl'
Requires-Dist: tqdm ; extra == 'tradeai_rl'
